[
	{
		"name": "Максим Волков",
		"img": "img/person_01.jpg",
		"stars": "<i class='fa fa-star'></i><i class='fa fa-star'></i><i class='fa fa-star'></i><i class='fa fa-star'></i></i><i class='fa fa-star grey-star'></i>",
		"date": "12.09",
		"text": "Сегодня был на замене передних колодок тормозов. До этого перезвонил на СТО и объя трения металл об мета)",
	"isClose": "false",
	"limit": "74"
	},
	{
		"name": "Сергей Исаев",
		"img": "img/person_02.jpg",
		"stars": "<i class='fa fa-star'></i><i class='fa fa-star'></i><i class='fa fa-star'></i><i class='fa fa-star'></i></i><i class='fa fa-star '></i>",
		"date": "12.09",
		"text": "Одним словом молодцы! Приехал (точнее притянул друга) на СТО за пол часа до закрытия в воскресенье, предварительно перезвонив менеджеру",
		"isClose": "false",
		"limit": "74"
	},
	{
		"name": "Генадий Наумов",
		"img": "img/person_03.jpg",
		"stars": "<i class='fa fa-star'></i><i class='fa fa-star'></i><i class='fa fa-star'></i><i class='fa fa-star'></i></i><i class='fa fa-star grey-star'></i>",
		"date": "12.09",
		"text": "Одним словом молодцы!",
		"isClose": "false",
		"limit": "74"
	},
	{
		"name": "Антон Давыдов",
		"img": "img/person_04.jpg",
		"stars": "<i class='fa fa-star'></i><i class='fa fa-star'></i><i class='fa fa-star'></i><i class='fa fa-star'></i></i><i class='fa fa-star '></i>",
		"date": "12.09",
		"text": "Сегодня был на замене передних колодок тормозов. До этого перезвонил на СТО и объя трения металл об металл)",
	"isClose": "false",
	"limit": "74"
	},
	{
		"name": "Никита Каменев",
		"img": "img/person_05.jpg",
		"stars": "<i class='fa fa-star'></i><i class='fa fa-star'></i><i class='fa fa-star'></i><i class='fa fa-star'></i></i><i class='fa fa-star grey-star'></i>",
		"date": "12.09",
		"text": "Одним словом молодцы! Приехал (точнее притянул друга) на СТО за пол часа до закрытия в воскресенье, предварительно перезвонив менеджеру",
		"isClose": "false",
		"limit": "74"
	},
	{
		"name": "Петр Шмелев",
		"img": "img/person_06.jpg",
		"stars": "<i class='fa fa-star'></i><i class='fa fa-star'></i><i class='fa fa-star'></i><i class='fa fa-star'></i></i><i class='fa fa-star '></i>",
		"date": "12.09",
		"text": "Одним словом молодцы!",
		"isClose": "false",
		"limit": "74"
	}
]